FollowLink/__init__.py
FollowLink/followlink.py
followlink-1.0.dist-info/LICENSE
followlink-1.0.dist-info/METADATA
followlink-1.0.dist-info/WHEEL
followlink-1.0.dist-info/entry_points.txt
followlink-1.0.dist-info/top_level.txt
followlink-1.0.dist-info/RECORD
