Metadata-Version: 2.1
Name: followlink
Version: 1.0
Summary: A tool to follow URL redirects and analyze response codes
Home-page: https://github.com/malwarekid/followlink
Author: Nitin Sharma
Author-email: nitinsharmahd123@gmail.com
License: MIT
Classifier: Programming Language :: Python :: 3
Classifier: License :: OSI Approved :: MIT License
Classifier: Operating System :: OS Independent
Requires-Python: >=3.6
License-File: LICENSE
Requires-Dist: requests
Requires-Dist: colorama
